pysrtkit/__init__.py
pysrtkit/_modidx.py
pysrtkit/srtfile.py
pysrtkit-0.0.4.dist-info/licenses/LICENSE
pysrtkit-0.0.4.dist-info/METADATA
pysrtkit-0.0.4.dist-info/WHEEL
pysrtkit-0.0.4.dist-info/entry_points.txt
pysrtkit-0.0.4.dist-info/top_level.txt
pysrtkit-0.0.4.dist-info/RECORD
